hvac_stability/__init__.py
hvac_stability/cli.py
hvac_stability-0.1.1.dist-info/METADATA
hvac_stability-0.1.1.dist-info/WHEEL
hvac_stability-0.1.1.dist-info/entry_points.txt
hvac_stability-0.1.1.dist-info/RECORD
