Metadata-Version: 2.4
Name: hvac-stability
Version: 0.1.1
Summary: A Python CLI tool for monitoring and managing HVAC device settings using the Kumo cloud API
Requires-Python: >=3.13
Requires-Dist: click>=8.2.1
Requires-Dist: environ-config>=24.1.0
Requires-Dist: pykumo>=0.3.11
Requires-Dist: typer>=0.16.0
